ccmixterdl/__init__.py
ccmixterdl/ccmixterdl.py
ccmixterdl/from ccmixterdl import main.py
ccmixter_dl-0.0.8.dist-info/LICENSE
ccmixter_dl-0.0.8.dist-info/METADATA
ccmixter_dl-0.0.8.dist-info/WHEEL
ccmixter_dl-0.0.8.dist-info/top_level.txt
ccmixter_dl-0.0.8.dist-info/RECORD
