Metadata-Version: 2.1
Name: ccmixter-dl
Version: 0.0.8
Summary: A small example package
Home-page: https://github.com/tjthejuggler
Author: tjthejuggler
Author-email: tjthejuggler@gmail.com
Project-URL: Bug Tracker, https://github.com/tjthejuggler/issues
Classifier: Programming Language :: Python :: 3
Classifier: License :: OSI Approved :: MIT License
Classifier: Operating System :: OS Independent
Requires-Python: >=3.6
License-File: LICENSE
